{
  "war": [
    {"war_num": "675.5", "war_name": "Negus Mikael Revolt", "war_type_code": "4.0", "war_type": "Intra-State War", "war_sub_type": "Civil War (for central control)", "total_participants": "2", "start_year": "1916.0", "end_year": "1917.0", "lagging_war": "nan", "leading_war": "nan", "ongoing_war": "0.0", "start_date": "1916-10-07 00:00:00", "end_date": "1917-08-27 00:00:00", "total_days_in_war": "324"}
  ],
  "nodes": [
    {"id": "0", "war_type_code": "4.0", "c_code": "530.0", "participant": "Ethiopia", "side": "1.0", "battle_deaths": "10000.0", "start_date": "1916-10-07 00:00:00", "start_year": "1916.0", "end_date": "1917-08-27 00:00:00", "end_year": "1917.0", "days_at_war": "324", "lagging_war": "nan", "leading_war": "nan", "ongoing_participation": "0.0", "peak_forces_available": "250000.0", "peak_battle_forces": "50000.0", "alliances_x": "0.0", "defense_alliances_x": "0.0", "entente_alliances_x": "0.0", "neutrality_alliances_x": "0.0", "money_flow_in_x": "-387000000.0", "money_flow_out_x": "-387000000.0", "imports_x": "0.0", "exports_x": "0.0", "military_expenditure_x": "nan", "military_personnel_x": "250000.0", "iron_steel_production_x": "0.0", "prim_energy_consumption_x": "0.0", "total_population_x": "9281000.0", "urban_population_x": "0.0", "urban_pop_growth_rate_x": "0.0", "cinc_score_x": "0.0032181999999999996", "alliances_y": "0.0", "defense_alliances_y": "0.0", "entente_alliances_y": "0.0", "neutrality_alliances_y": "0.0", "money_flow_in_y": "-387000000.0", "money_flow_out_y": "-387000000.0", "imports_y": "0.0", "exports_y": "0.0", "military_expenditure_y": "nan", "military_personnel_y": "250000.0", "iron_steel_production_y": "0.0", "prim_energy_consumption_y": "0.0", "total_population_y": "9368000.0", "urban_population_y": "0.0", "urban_pop_growth_rate_y": "0.0", "cinc_score_y": "0.0030671999999999995"},
    {"id": "1", "war_type_code": "4.0", "c_code": "-8.0", "participant": "Negus Mikael-led Rebels", "side": "2.0", "battle_deaths": "10000.0", "start_date": "1916-10-07 00:00:00", "start_year": "1916.0", "end_date": "1917-08-27 00:00:00", "end_year": "1917.0", "days_at_war": "324", "lagging_war": "nan", "leading_war": "nan", "ongoing_participation": "0.0", "peak_forces_available": "nan", "peak_battle_forces": "100000.0", "alliances_x": "0.0", "defense_alliances_x": "0.0", "entente_alliances_x": "0.0", "neutrality_alliances_x": "0.0", "money_flow_in_x": "0.0", "money_flow_out_x": "0.0", "imports_x": "0.0", "exports_x": "0.0", "military_expenditure_x": "0.0", "military_personnel_x": "0.0", "iron_steel_production_x": "0.0", "prim_energy_consumption_x": "0.0", "total_population_x": "0.0", "urban_population_x": "0.0", "urban_pop_growth_rate_x": "0.0", "cinc_score_x": "0.0", "alliances_y": "0.0", "defense_alliances_y": "0.0", "entente_alliances_y": "0.0", "neutrality_alliances_y": "0.0", "money_flow_in_y": "0.0", "money_flow_out_y": "0.0", "imports_y": "0.0", "exports_y": "0.0", "military_expenditure_y": "0.0", "military_personnel_y": "0.0", "iron_steel_production_y": "0.0", "prim_energy_consumption_y": "0.0", "total_population_y": "0.0", "urban_population_y": "0.0", "urban_pop_growth_rate_y": "0.0", "cinc_score_y": "0.0"}
  ],
  "links": [
    {"source": "0", "target": "1", "first_year": "1916", "territory_exchange_x": "0.0", "colonial_contiguity_x": "0.0", "contiguity_x": "0.0", "alliance_x": "0.0", "defense_cooperation_agreements_x": "0.0", "inter_governmental_organizations_x": "0.0", "diplomatic_exchange_x": "0.0", "trade_relations_x": "0.0", "same_leader_type_x": "0.0", "military_leaders_x": "0.0", "communist_leaders_x": "0.0", "royal_leaders_x": "0.0", "unconstitutional_incumbents_x": "0.0", "both_democratic_regimes_x": "0.0", "dictatorships_x": "0.0", "collective_leaderships_x": "0.0", "same_incumbent_type_x": "0.0", "same_legislation_type_x": "0.0", "no_legislation_x": "0.0", "all_parties_banned_x": "0.0", "no_parties_x": "0.0", "single_party_states_x": "0.0", "regime_only_legislature_x": "0.0", "atop_x": "0.0", "mtops_x": "0.0", "last_year": "1916", "territory_exchange_y": "0.0", "colonial_contiguity_y": "0.0", "contiguity_y": "0.0", "alliance_y": "0.0", "defense_cooperation_agreements_y": "0.0", "inter_governmental_organizations_y": "0.0", "diplomatic_exchange_y": "0.0", "trade_relations_y": "0.0", "same_leader_type_y": "0.0", "military_leaders_y": "0.0", "communist_leaders_y": "0.0", "royal_leaders_y": "0.0", "unconstitutional_incumbents_y": "0.0", "both_democratic_regimes_y": "0.0", "dictatorships_y": "0.0", "collective_leaderships_y": "0.0", "same_incumbent_type_y": "0.0", "same_legislation_type_y": "0.0", "no_legislation_y": "0.0", "all_parties_banned_y": "0.0", "no_parties_y": "0.0", "single_party_states_y": "0.0", "regime_only_legislature_y": "0.0", "atop_y": "0.0", "mtops_y": "0.0", "territory_exchange_z": "0.0", "colonial_contiguity_z": "0.0", "contiguity_z": "0.0", "alliance_z": "0.0", "defense_cooperation_agreements_z": "0.0", "inter_governmental_organizations_z": "0.0", "diplomatic_exchange_z": "0.0", "trade_relations_z": "0.0", "same_leader_type_z": "0.0", "military_leaders_z": "0.0", "communist_leaders_z": "0.0", "royal_leaders_z": "0.0", "unconstitutional_incumbents_z": "0.0", "both_democratic_regimes_z": "0.0", "dictatorships_z": "0.0", "collective_leaderships_z": "0.0", "same_incumbent_type_z": "0.0", "same_legislation_type_z": "0.0", "no_legislation_z": "0.0", "all_parties_banned_z": "0.0", "no_parties_z": "0.0", "single_party_states_z": "0.0", "regime_only_legislature_z": "0.0", "atop_z": "0.0", "mtops_z": "0.0"}

  ]
}