{
  "war": [
    {"war_name": "Second Laotian, Phase 2", "war_num": "170.0", "war_type_code": "1", "war_type": "Inter-State War", "war_sub_type": "", "war_start_date": "1968-01-13 00:00:00", "war_end": "1973-04-17 00:00:00", "total_days_in_war": "1921", "lagging_war": "nan", "leading_war": "nan", "ongoing_war": "0.0"}
  ],
  "nodes": [
    {"country": "United States of America", "country_code": "2", "side": "2", "battle_deaths": "375.0", "start_year": "1968.0", "start_date": "1968-01-13 00:00:00", "end_year": "1973.0", "end_date": "1973-04-17 00:00:00", "days_at_war": "1921", "peak_forces_available": "nan", "peak_battle_forces": "nan", "alliances_x": "14.0", "alliances_y": "15.0", "non_aggression_alliances_x": "5.0", "non_aggression_alliances_y": "5.0", "entente_alliances_x": "8.0", "entente_alliances_y": "9.0", "money_flow_out_x": "31065712739.889", "money_flow_out_y": "65631211126.10058", "money_flow_in_x": "33848797786.210003", "money_flow_in_y": "69571890660.80002", "imports_x": "35368.3", "imports_y": "74296.6", "exports_x": "34567.6", "exports_y": "71431.7", "military_expenditure_x": "80732000000.0", "military_expenditure_y": "78385000000.0", "military_personnel_x": "3550000.0", "military_personnel_y": "2206000.0", "prim_energy_consumption_x": "4188706000000.0", "prim_energy_consumption_y": "2490304.0", "iron_steel_production_x": "238524000000.0", "iron_steel_production_y": "273608000000.0", "total_population_x": "200706000.0", "total_population_y": "211909000.0", "urban_population_x": "50765000.0", "urban_population_y": "55743000.0", "cinc_score_x": "0.20341189999999998", "cinc_score_y": "0.1588194"},
    {"country": "Thailand", "country_code": "800", "side": "2", "battle_deaths": "nan", "start_year": "1970.0", "start_date": "1970-03-17 00:00:00", "end_year": "1973.0", "end_date": "1973-04-17 00:00:00", "days_at_war": "1127", "peak_forces_available": "nan", "peak_battle_forces": "nan", "alliances_x": "1.0", "alliances_y": "1.0", "non_aggression_alliances_x": "0.0", "non_aggression_alliances_y": "0.0", "entente_alliances_x": "1.0", "entente_alliances_y": "1.0", "money_flow_out_x": "1122422989.9036005", "money_flow_out_y": "1793695014.1703", "money_flow_in_x": "604529464.7335999", "money_flow_in_y": "1305778919.8533998", "imports_x": "1298.52", "imports_y": "2032.2", "exports_x": "709.93", "exports_y": "1562.3", "military_expenditure_x": "239019000.0", "military_expenditure_y": "302522000.0", "military_personnel_x": "175000.0", "military_personnel_y": "233000.0", "prim_energy_consumption_x": "29092000000.0", "prim_energy_consumption_y": "21468.0", "iron_steel_production_x": "80000000.0", "iron_steel_production_y": "380000000.0", "total_population_x": "36370000.0", "total_population_y": "39693000.0", "urban_population_x": "2313000.0", "urban_population_y": "2612000.0", "cinc_score_x": "0.0038904000000000005", "cinc_score_y": "0.0044210000000000005"},
    {"country": "Laos", "country_code": "812", "side": "2", "battle_deaths": "11250.0", "start_year": "1968.0", "start_date": "1968-01-13 00:00:00", "end_year": "1973.0", "end_date": "1973-04-17 00:00:00", "days_at_war": "1921", "peak_forces_available": "nan", "peak_battle_forces": "nan", "alliances_x": "0.0", "alliances_y": "0.0", "non_aggression_alliances_x": "0.0", "non_aggression_alliances_y": "0.0", "entente_alliances_x": "0.0", "entente_alliances_y": "0.0", "money_flow_out_x": "-419093999.9799999", "money_flow_out_y": "-459060000.08630013", "money_flow_in_x": "-554251999.9710001", "money_flow_in_y": "-552478001.8219001", "imports_x": "53.70399999999999", "imports_y": "56.358999999999995", "exports_x": "6.039", "exports_y": "5.063", "military_expenditure_x": "40000000.0", "military_expenditure_y": "17150000.0", "military_personnel_x": "62000.0", "military_personnel_y": "71000.0", "prim_energy_consumption_x": "8000000.0", "prim_energy_consumption_y": "1667.0", "iron_steel_production_x": "0.0", "iron_steel_production_y": "0.0", "total_population_x": "2825000.0", "total_population_y": "3181000.0", "urban_population_x": "143000.0", "urban_population_y": "178000.0", "cinc_score_x": "0.0006299", "cinc_score_y": "0.0006795"},
    {"country": "Vietnam", "country_code": "816", "side": "1", "battle_deaths": "2250.0", "start_year": "1968.0", "start_date": "1968-01-13 00:00:00", "end_year": "1973.0", "end_date": "1973-04-17 00:00:00", "days_at_war": "1921", "peak_forces_available": "nan", "peak_battle_forces": "nan", "alliances_x": "0.0", "alliances_y": "0.0", "non_aggression_alliances_x": "0.0", "non_aggression_alliances_y": "0.0", "entente_alliances_x": "0.0", "entente_alliances_y": "0.0", "money_flow_out_x": "47453993.63009999", "money_flow_out_y": "150318006.8028", "money_flow_in_x": "-501990000.001", "money_flow_in_y": "-300784000.4240001", "imports_x": "92.242", "imports_y": "304.515", "exports_x": "0.179", "exports_y": "12.213", "military_expenditure_x": "500000000.0", "military_expenditure_y": "290000000.0", "military_personnel_x": "447000.0", "military_personnel_y": "630000.0", "prim_energy_consumption_x": "0.0", "prim_energy_consumption_y": "8243.0", "iron_steel_production_x": "500000000.0", "iron_steel_production_y": "490000000.0", "total_population_x": "20280000.0", "total_population_y": "22481000.0", "urban_population_x": "1620000.0", "urban_population_y": "1065000.0", "cinc_score_x": "0.0059306", "cinc_score_y": "0.0056838999999999995"}
  ],
  "links": [
    {"source": 3, "target": 2, "first_year": 1967.0, "defense_alliance": 0.0, "neutrality_alliance": 0.0, "entente_alliance": 0.0, "land_contiguity": 0, "sea_contiguity": 0, "total_contiguity": 0, "bond": 1},
    {"source": 0, "target": 3, "first_year": 1968.0, "defense_alliance": 0.0, "neutrality_alliance": 0.0, "entente_alliance": 0.0, "land_contiguity": 0, "sea_contiguity": 0, "total_contiguity": 0, "bond": 1},
    {"source": 1, "target": 3, "first_year": 1970.0, "defense_alliance": 0.0, "neutrality_alliance": 0.0, "entente_alliance": 0.0, "land_contiguity": 0, "sea_contiguity": 0, "total_contiguity": 0, "bond": 1}

  ]
}